{
 "cells": [
  {
   "cell_type": "code",
   "execution_count": 1,
   "id": "fdf09a51",
   "metadata": {},
   "outputs": [],
   "source": [
    "def dobro(x):\n",
    "    return x*2\n"
   ]
  },
  {
   "cell_type": "code",
   "execution_count": 2,
   "id": "f8b54a54",
   "metadata": {},
   "outputs": [],
   "source": [
    "dobro2 = lambda x: x*2"
   ]
  },
  {
   "cell_type": "code",
   "execution_count": 4,
   "id": "68162269",
   "metadata": {},
   "outputs": [
    {
     "name": "stdout",
     "output_type": "stream",
     "text": [
      "          0 RESUME                   0\n",
      "          2 LOAD_FAST                0\n",
      "          4 LOAD_CONST               1\n",
      "          6 BINARY_OP                5 (*)\n",
      "         10 RETURN_VALUE\n"
     ]
    }
   ],
   "source": [
    "from dis import dis\n",
    "dis(dobro.__code__.co_code)"
   ]
  },
  {
   "cell_type": "code",
   "execution_count": 5,
   "id": "9096cebe",
   "metadata": {},
   "outputs": [
    {
     "name": "stdout",
     "output_type": "stream",
     "text": [
      "          0 RESUME                   0\n",
      "          2 LOAD_FAST                0\n",
      "          4 LOAD_CONST               1\n",
      "          6 BINARY_OP                5 (*)\n",
      "         10 RETURN_VALUE\n"
     ]
    }
   ],
   "source": [
    "from dis import dis\n",
    "dis(dobro2.__code__.co_code)"
   ]
  },
  {
   "cell_type": "code",
   "execution_count": 6,
   "id": "fae8df15",
   "metadata": {},
   "outputs": [
    {
     "data": {
      "text/plain": [
       "'dobro'"
      ]
     },
     "execution_count": 6,
     "metadata": {},
     "output_type": "execute_result"
    }
   ],
   "source": [
    "dobro.__name__"
   ]
  },
  {
   "cell_type": "code",
   "execution_count": 7,
   "id": "8dcba245",
   "metadata": {},
   "outputs": [
    {
     "data": {
      "text/plain": [
       "'<lambda>'"
      ]
     },
     "execution_count": 7,
     "metadata": {},
     "output_type": "execute_result"
    }
   ],
   "source": [
    "dobro2.__name__"
   ]
  }
 ],
 "metadata": {
  "kernelspec": {
   "display_name": "Python 3",
   "language": "python",
   "name": "python3"
  },
  "language_info": {
   "codemirror_mode": {
    "name": "ipython",
    "version": 3
   },
   "file_extension": ".py",
   "mimetype": "text/x-python",
   "name": "python",
   "nbconvert_exporter": "python",
   "pygments_lexer": "ipython3",
   "version": "3.12.1"
  }
 },
 "nbformat": 4,
 "nbformat_minor": 5
}
